{
  "$schema": "https://json-structure.org/meta/core/v0/#",
  "$id": "https://raw.githubusercontent.com/api-evangelist/amplitude/refs/heads/main/json-structure/dsar-api-deletion-response-structure.json",
  "name": "DeletionResponse",
  "description": "DeletionResponse schema from Amplitude Data Subject Access Request API",
  "type": "object",
  "properties": {
    "day": {
      "type": "date",
      "description": "The day the deletion job is scheduled for processing."
    },
    "status": {
      "type": "string",
      "description": "The status of the deletion request."
    }
  }
}